dirrank/__init__.py
dirrank-0.0.1.dist-info/LICENSE
dirrank-0.0.1.dist-info/METADATA
dirrank-0.0.1.dist-info/WHEEL
dirrank-0.0.1.dist-info/top_level.txt
dirrank-0.0.1.dist-info/RECORD
